[
    {
        "fix_commit_hash": "674b2a261f7fe7655ed6223c0f759eb340b4d27c",
        "repo_name": "pulsar",
        "best_scenario_issue_date": "2018-01-12T14:51:25-08:00",
        "matched": [
            "5bf96a71e90f92791e14296dbbb152aaa026650e"
        ]
    },
    {
        "fix_commit_hash": "ec46e1a4c5b3f37b743397d356ff4c471de4caed",
        "repo_name": "pulsar",
        "best_scenario_issue_date": "2018-01-10T12:08:14-08:00",
        "matched": [
            "493e54ae1fef1fd41f4f7a2f0797f06e5034a8cc"
        ]
    },
    {
        "fix_commit_hash": "3db8b7392b1be22544117ea336dd46cc85c61ba0",
        "repo_name": "pulsar",
        "best_scenario_issue_date": "2018-10-23T17:29:04-07:00",
        "matched": [
            "75d9fe2eeed76e7e085757e3facf0ee3db54959e"
        ]
    },
    {
        "fix_commit_hash": "4b37fdaeb1f0a286e591e44120da46d33a1c0cc5",
        "repo_name": "pulsar",
        "best_scenario_issue_date": "2018-06-07T13:36:00-07:00",
        "matched": [
            "cb74f216f4905570df151024ee88c09d5db4ae88"
        ]
    },
    {
        "fix_commit_hash": "c308bd5f81a1eb2c63d4d2dc3ddb652690a74bec",
        "repo_name": "pulsar",
        "best_scenario_issue_date": "2018-02-26T01:34:55-08:00",
        "matched": [
            "cd6f5396853f984e6fe60dad95b635cbdc7143dc"
        ]
    },
    {
        "fix_commit_hash": "9605aede8aa1e14783d480a2fc6a55fe8ceaa67a",
        "repo_name": "pulsar",
        "best_scenario_issue_date": "2019-07-19T22:59:03+09:00",
        "matched": [
            "548c726b8e7f0e163b1132c9ada6ba83d6bec572"
        ]
    },
    {
        "fix_commit_hash": "6e7d1a83c3c2737610f01cb372f61e2b830a62f7",
        "repo_name": "pulsar",
        "best_scenario_issue_date": "2020-08-14T09:22:44+08:00",
        "matched": [
            "e7195ebf5c0bcc7a3dda1446e78f2284e27d74bf"
        ]
    },
    {
        "fix_commit_hash": "16d8177c05801c7eac367ab58a81b07a8135491d",
        "repo_name": "pulsar",
        "best_scenario_issue_date": "2017-04-05T10:14:40-07:00",
        "matched": []
    },
    {
        "fix_commit_hash": "7de9992b6c047fbdda7ab47ba83b97156f881d12",
        "repo_name": "pulsar",
        "best_scenario_issue_date": "2021-08-25T11:23:13+03:00",
        "matched": [
            "ac0e15d24e2a40a20d6889bf477ae9bd52bb37eb"
        ]
    },
    {
        "fix_commit_hash": "12f896ee70f5911ee04e5dafde04ede1921ccb0b",
        "repo_name": "pulsar",
        "best_scenario_issue_date": "2017-01-10T04:32:56-08:00",
        "matched": [
            "4dbe9d34235853bc64eb3f38816ffe014308492d"
        ]
    }
]