[{"repo_name": "pulsar", "repo_url": "apache/pulsar", "issue_html_url": "https://github.com/apache/pulsar/issues/6897", "earliest_issue_date": "2020-05-06T14:33:11Z", "fix_commit_hash": "d4d380a8e4372037c3e479f351562677cf2e4092", "tipo": "PR", "commit_author": "\u5189\u5c0f\u9f99", "commiter": "GitHub", "commit_date": "2020-05-25T16:45:56+08:00", "committer_data": "2020-05-25T16:45:56+08:00", "changed_files": 3, "deletions": 11, "insertions": 46, "lines": 57, "dmm_unit_size": null, "dmm_unit_complexity": null, "dmm_unit_interfacing": null, "files_exts": ["properties", "java", "md"], "inducing_commit_hash_pyszz": []}, {"repo_name": "pulsar", "repo_url": "apache/pulsar", "issue_html_url": "https://github.com/apache/pulsar/issues/6892", "earliest_issue_date": "2020-05-06T12:40:31Z", "fix_commit_hash": "1aaa148125a851536326d33f59434e3aae456096", "tipo": "PR", "commit_author": "liudezhi", "commiter": "GitHub", "commit_date": "2020-05-13T13:07:44+08:00", "committer_data": "2020-05-13T13:07:44+08:00", "changed_files": 1, "deletions": 4, "insertions": 2, "lines": 6, "dmm_unit_size": 1.0, "dmm_unit_complexity": 0.0, "dmm_unit_interfacing": 0.0, "files_exts": ["java"], "inducing_commit_hash_pyszz": ["5f2dfc1fd73a937f505a25a74fa9edd6a5a0e324"]}, {"repo_name": "pulsar", "repo_url": "apache/pulsar", "issue_html_url": "https://github.com/apache/pulsar/issues/6891", "earliest_issue_date": "2020-05-06T11:43:14Z", "fix_commit_hash": "204f3271914f5fbdeb7bf0a7ff5a71e77b8cccbf", "tipo": "PR", "commit_author": "lipenghui", "commiter": "GitHub", "commit_date": "2020-05-09T03:21:28+08:00", "committer_data": "2020-05-08T12:21:28-07:00", "changed_files": 15, "deletions": 37, "insertions": 294, "lines": 331, "dmm_unit_size": 0.034482758620689655, "dmm_unit_complexity": 0.8850574712643678, "dmm_unit_interfacing": 0.8505747126436781, "files_exts": ["java", "java", "java", "java", "java", "java", "java", "java", "java", "java", "java", "java", "java", "java", "md"], "inducing_commit_hash_pyszz": ["9b553242e580b22524ca17c57a5cd4b2f1ed0f3b"]}, {"repo_name": "pulsar", "repo_url": "apache/pulsar", "issue_html_url": "https://github.com/apache/pulsar/issues/6887", "earliest_issue_date": "2020-05-06T06:59:25Z", "fix_commit_hash": "a24203cc140a97940bca99ca7a761c7e5e78c49c", "tipo": "PR", "commit_author": "Jiechuan Chen", "commiter": "GitHub", "commit_date": "2020-05-12T18:53:06+08:00", "committer_data": "2020-05-12T18:53:06+08:00", "changed_files": 2, "deletions": 0, "insertions": 11, "lines": 11, "dmm_unit_size": 0.0, "dmm_unit_complexity": 0.0, "dmm_unit_interfacing": 0.0, "files_exts": ["java", "java"], "inducing_commit_hash_pyszz": []}, {"repo_name": "pulsar", "repo_url": "apache/pulsar", "issue_html_url": "https://github.com/apache/pulsar/issues/6873", "earliest_issue_date": "2020-05-04T20:28:48Z", "fix_commit_hash": "8381371a3cdae52521c8d50ca053d7510989fb33", "tipo": "PR", "commit_author": "Alexandre DUVAL", "commiter": "GitHub", "commit_date": "2020-05-09T02:46:00+02:00", "committer_data": "2020-05-08T17:46:00-07:00", "changed_files": 1, "deletions": 1, "insertions": 15, "lines": 16, "dmm_unit_size": 0.0, "dmm_unit_complexity": 0.0, "dmm_unit_interfacing": 1.0, "files_exts": ["java"], "inducing_commit_hash_pyszz": ["09e3ed8aa15579d2fb265ce039b8f8bdb5b9f59f"]}, {"repo_name": "pulsar", "repo_url": "apache/pulsar", "issue_html_url": "https://github.com/apache/pulsar/issues/6872", "earliest_issue_date": "2020-05-04T18:29:40Z", "fix_commit_hash": "30e26f84fbd35c2f88665195c426a73336a6fc1f", "tipo": "PR", "commit_author": "Addison Higham", "commiter": "GitHub", "commit_date": "2020-05-06T01:15:19-06:00", "committer_data": "2020-05-06T15:15:19+08:00", "changed_files": 1, "deletions": 2, "insertions": 2, "lines": 4, "dmm_unit_size": null, "dmm_unit_complexity": null, "dmm_unit_interfacing": null, "files_exts": ["java"], "inducing_commit_hash_pyszz": ["fbdf0383492277fbb0589a5485e2171d1f3c3568"]}, {"repo_name": "pulsar", "repo_url": "apache/pulsar", "issue_html_url": "https://github.com/apache/pulsar/issues/6854", "earliest_issue_date": "2020-05-01T01:27:50Z", "fix_commit_hash": "561868d4c441d654ab795a9386d8e9a5e28f03dd", "tipo": "PR", "commit_author": "hangc0276", "commiter": "GitHub", "commit_date": "2020-05-11T08:41:11+08:00", "committer_data": "2020-05-11T08:41:11+08:00", "changed_files": 4, "deletions": 29, "insertions": 128, "lines": 157, "dmm_unit_size": 0.0, "dmm_unit_complexity": 0.4470588235294118, "dmm_unit_interfacing": 0.38823529411764707, "files_exts": ["java", "java", "java", "java"], "inducing_commit_hash_pyszz": ["571b68464e25e8e71d3d278f58ba3a3df0c67a5b"]}, {"repo_name": "pulsar", "repo_url": "apache/pulsar", "issue_html_url": "https://github.com/apache/pulsar/issues/14882", "earliest_issue_date": "2022-03-25T16:27:18Z", "fix_commit_hash": "768961b3d7209f28c09f86c6682b6a3fa0658544", "tipo": "PR", "commit_author": "Nicol\u00f2 Boschi", "commiter": "GitHub", "commit_date": "2022-07-12T22:27:54+02:00", "committer_data": "2022-07-12T22:27:54+02:00", "changed_files": 1, "deletions": 1, "insertions": 8, "lines": 9, "dmm_unit_size": 0.5, "dmm_unit_complexity": 0.5, "dmm_unit_interfacing": 0.5, "files_exts": ["java"], "inducing_commit_hash_pyszz": ["94ec03111369e694f432ca219be77820648d2188"]}, {"repo_name": "pulsar", "repo_url": "apache/pulsar", "issue_html_url": "https://github.com/apache/pulsar/issues/14880", "earliest_issue_date": "2022-03-25T15:20:20Z", "fix_commit_hash": "4e62ffc15714cfa49ed441f3ba7ededb866b9062", "tipo": "PR", "commit_author": "gaozhangmin", "commiter": "GitHub", "commit_date": "2022-03-29T01:00:20+08:00", "committer_data": "2022-03-29T01:00:20+08:00", "changed_files": 2, "deletions": 7, "insertions": 13, "lines": 20, "dmm_unit_size": 1.0, "dmm_unit_complexity": 1.0, "dmm_unit_interfacing": 1.0, "files_exts": ["java", "java"], "inducing_commit_hash_pyszz": ["08d8e95bef423cdce0dc2660377b5e2a8d371d88"]}, {"repo_name": "pulsar", "repo_url": "apache/pulsar", "issue_html_url": "https://github.com/apache/pulsar/issues/14879", "earliest_issue_date": "2022-03-25T14:34:46Z", "fix_commit_hash": "e8d52fdb14dca62e7f0d7eb933bb7dc7fb3e916e", "tipo": "PR", "commit_author": "ran", "commiter": "GitHub", "commit_date": "2022-03-30T06:30:38+08:00", "committer_data": "2022-03-29T15:30:38-07:00", "changed_files": 2, "deletions": 1, "insertions": 126, "lines": 127, "dmm_unit_size": 0.9833333333333333, "dmm_unit_complexity": 0.9833333333333333, "dmm_unit_interfacing": 0.9833333333333333, "files_exts": ["java", "java"], "inducing_commit_hash_pyszz": ["d86db3f4ec4fb6bd04216a123cde2fee5c43f9d9"]}]