[
    {
        "repo_name": "pulsar",
        "repo_url": "apache/pulsar",
        "issue_html_url": "https://github.com/apache/pulsar/issues/4994",
        "earliest_issue_date": "2019-08-21T07:26:09Z",
        "fix_commit_hash": "e0ea6b53a2f6f655563df87afad4540c53e6bb0c",
        "tipo": "PR",
        "commit_author": "Marvin Cai",
        "commiter": "Jia Zhai",
        "commit_date": "2019-11-06T00:45:57-08:00",
        "committer_data": "2019-11-06T16:45:57+08:00",
        "changed_files": 8,
        "deletions": 40,
        "insertions": 226,
        "lines": 266,
        "dmm_unit_size": 1.0,
        "dmm_unit_complexity": 0.0,
        "dmm_unit_interfacing": 0.0,
        "files_exts": [
            "java",
            "java",
            "java",
            "java",
            "java",
            "cc",
            "md",
            "md"
        ]
    },
    {
        "repo_name": "pulsar",
        "repo_url": "apache/pulsar",
        "issue_html_url": "https://github.com/apache/pulsar/issues/4980",
        "earliest_issue_date": "2019-08-20T02:14:19Z",
        "fix_commit_hash": "36d4c68f78b42759ccc4186927e6974c3cfb13a9",
        "tipo": "PR",
        "commit_author": "feynmanlin",
        "commiter": "GitHub",
        "commit_date": "2020-09-23T15:26:51+08:00",
        "committer_data": "2020-09-23T02:26:51-05:00",
        "changed_files": 6,
        "deletions": 1,
        "insertions": 139,
        "lines": 140,
        "dmm_unit_size": 0.4943820224719101,
        "dmm_unit_complexity": 0.4943820224719101,
        "dmm_unit_interfacing": 1.0,
        "files_exts": [
            "java",
            "java",
            "java",
            "java",
            "java",
            "java"
        ]
    },
    {
        "repo_name": "pulsar",
        "repo_url": "apache/pulsar",
        "issue_html_url": "https://github.com/apache/pulsar/issues/4971",
        "earliest_issue_date": "2019-08-16T09:28:50Z",
        "fix_commit_hash": "4cf35167f3e267304c014d936bf34b588a8e78b4",
        "tipo": "PR",
        "commit_author": "Rui Fu",
        "commiter": "Sijie Guo",
        "commit_date": "2019-08-22T04:44:47+08:00",
        "committer_data": "2019-08-22T04:44:47+08:00",
        "changed_files": 3,
        "deletions": 1,
        "insertions": 34,
        "lines": 35,
        "dmm_unit_size": null,
        "dmm_unit_complexity": null,
        "dmm_unit_interfacing": null,
        "files_exts": [
            "docker/pulsar/Dockerfile",
            "xml",
            "sh"
        ]
    },
    {
        "repo_name": "pulsar",
        "repo_url": "apache/pulsar",
        "issue_html_url": "https://github.com/apache/pulsar/issues/946",
        "earliest_issue_date": "2017-12-06T20:11:15Z",
        "fix_commit_hash": "df9d4e553898e9025ca75c857d24412456cfcd65",
        "tipo": "PR",
        "commit_author": "sschepens",
        "commiter": "Matteo Merli",
        "commit_date": "2017-12-21T20:00:03-03:00",
        "committer_data": "2017-12-22T00:00:03+01:00",
        "changed_files": 3,
        "deletions": 48,
        "insertions": 120,
        "lines": 168,
        "dmm_unit_size": 0.0,
        "dmm_unit_complexity": 0.8688524590163934,
        "dmm_unit_interfacing": 0.8688524590163934,
        "files_exts": [
            "java",
            "java",
            "java"
        ]
    },
    {
        "repo_name": "pulsar",
        "repo_url": "apache/pulsar",
        "issue_html_url": "https://github.com/apache/pulsar/issues/935",
        "earliest_issue_date": "2017-12-02T14:35:14Z",
        "fix_commit_hash": "11a6872974fee4a078f9c1823613bb586d012d58",
        "tipo": "PR",
        "commit_author": "Matteo Merli",
        "commiter": "Rajan Dhabalia",
        "commit_date": "2017-12-05T11:59:27-08:00",
        "committer_data": "2017-12-05T11:59:27-08:00",
        "changed_files": 1,
        "deletions": 0,
        "insertions": 1,
        "lines": 1,
        "dmm_unit_size": null,
        "dmm_unit_complexity": null,
        "dmm_unit_interfacing": null,
        "files_exts": [
            "xml"
        ]
    },
    {
        "repo_name": "pulsar",
        "repo_url": "apache/pulsar",
        "issue_html_url": "https://github.com/apache/pulsar/issues/867",
        "earliest_issue_date": "2017-10-27T18:58:07Z",
        "fix_commit_hash": "5a4dd113822913431406844051a3d592d22fca84",
        "tipo": "PR",
        "commit_author": "Rajan Dhabalia",
        "commiter": "Matteo Merli",
        "commit_date": "2017-10-31T14:44:35-07:00",
        "committer_data": "2017-10-31T14:44:35-07:00",
        "changed_files": 3,
        "deletions": 15,
        "insertions": 21,
        "lines": 36,
        "dmm_unit_size": 0.0,
        "dmm_unit_complexity": 0.3333333333333333,
        "dmm_unit_interfacing": 1.0,
        "files_exts": [
            "java",
            "java",
            "java"
        ]
    },
    {
        "repo_name": "pulsar",
        "repo_url": "apache/pulsar",
        "issue_html_url": "https://github.com/apache/pulsar/issues/834",
        "earliest_issue_date": "2017-10-17T18:33:47Z",
        "fix_commit_hash": "1d9d596ebe65dc6cefae5d5406179146c785cbb4",
        "tipo": "PR",
        "commit_author": "Andrews",
        "commiter": "Matteo Merli",
        "commit_date": "2017-10-17T23:02:45-07:00",
        "committer_data": "2017-10-17T23:02:45-07:00",
        "changed_files": 1,
        "deletions": 6,
        "insertions": 7,
        "lines": 13,
        "dmm_unit_size": 0.0,
        "dmm_unit_complexity": 1.0,
        "dmm_unit_interfacing": 0.0,
        "files_exts": [
            "java"
        ]
    },
    {
        "repo_name": "pulsar",
        "repo_url": "apache/pulsar",
        "issue_html_url": "https://github.com/apache/pulsar/issues/814",
        "earliest_issue_date": "2017-10-05T18:24:13Z",
        "fix_commit_hash": "059149c494592a3913a4fb24ed6939e1b068fc58",
        "tipo": "PR",
        "commit_author": "Matteo Merli",
        "commiter": "GitHub",
        "commit_date": "2018-01-29T20:12:09-08:00",
        "committer_data": "2018-01-29T20:12:09-08:00",
        "changed_files": 1,
        "deletions": 29,
        "insertions": 23,
        "lines": 52,
        "dmm_unit_size": null,
        "dmm_unit_complexity": null,
        "dmm_unit_interfacing": null,
        "files_exts": [
            "java"
        ]
    },
    {
        "repo_name": "pulsar",
        "repo_url": "apache/pulsar",
        "issue_html_url": "https://github.com/apache/pulsar/issues/813",
        "earliest_issue_date": "2017-10-05T09:33:50Z",
        "fix_commit_hash": "9433f36768f3e027d25564444c746207d77bb647",
        "tipo": "PR",
        "commit_author": "massakam",
        "commiter": "Matteo Merli",
        "commit_date": "2017-11-07T02:46:20+09:00",
        "committer_data": "2017-11-06T09:46:20-08:00",
        "changed_files": 7,
        "deletions": 7,
        "insertions": 45,
        "lines": 52,
        "dmm_unit_size": 1.0,
        "dmm_unit_complexity": 1.0,
        "dmm_unit_interfacing": 1.0,
        "files_exts": [
            "bin/pulsar",
            "sh",
            "sh",
            "sh",
            "java",
            "java",
            "md"
        ]
    },
    {
        "repo_name": "pulsar",
        "repo_url": "apache/pulsar",
        "issue_html_url": "https://github.com/apache/pulsar/issues/776",
        "earliest_issue_date": "2017-09-21T00:01:35Z",
        "fix_commit_hash": "79a7790f90c4e1f8a4c51a51e4b7fc600992e43f",
        "tipo": "PR",
        "commit_author": "Matteo Merli",
        "commiter": "Rajan Dhabalia",
        "commit_date": "2017-09-20T19:50:29-07:00",
        "committer_data": "2017-09-20T19:50:29-07:00",
        "changed_files": 1,
        "deletions": 9,
        "insertions": 16,
        "lines": 25,
        "dmm_unit_size": 0.0,
        "dmm_unit_complexity": 1.0,
        "dmm_unit_interfacing": 1.0,
        "files_exts": [
            "cc"
        ]
    }
]