[
    {
        "fix_commit_hash": "ac10b006cf59308ae1a0bf8307ddcb2f5745cc11",
        "repo_name": "pulsar",
        "best_scenario_issue_date": "2019-07-18T12:00:33-07:00"
    },
    {
        "fix_commit_hash": "22d782463e8893187a7987d26965dbb4cd0be2a5",
        "repo_name": "pulsar",
        "best_scenario_issue_date": "2020-02-12T11:49:23-08:00"
    },
    {
        "fix_commit_hash": "9d08f64a827ad670c89cf708ddd409e1d5b5f763",
        "repo_name": "pulsar",
        "best_scenario_issue_date": "2021-04-01T10:46:40+08:00"
    },
    {
        "fix_commit_hash": "af932ed3e9f325cd0d36f57ffd1f4fd4d9f446ad",
        "repo_name": "pulsar",
        "best_scenario_issue_date": "2022-07-19T09:54:56+08:00"
    },
    {
        "fix_commit_hash": "e927839efc7c10ee40808a697d4dc4cd6d611d23",
        "repo_name": "pulsar",
        "best_scenario_issue_date": "2022-12-09T04:52:24+00:00"
    },
    {
        "fix_commit_hash": "2442071d36a4141101dd00c8666ffbdcbe3bbbe2",
        "repo_name": "pulsar",
        "best_scenario_issue_date": "2021-01-05T01:43:09+08:00"
    },
    {
        "fix_commit_hash": "fc86f3b5f066bc71840d42d1163e85f048216aa7",
        "repo_name": "pulsar",
        "best_scenario_issue_date": "2023-09-12T16:26:42+08:00"
    },
    {
        "fix_commit_hash": "1a1a6e3b06711248663b3a960c302c9dc2bf02e6",
        "repo_name": "pulsar",
        "best_scenario_issue_date": "2018-02-24T09:15:08-08:00"
    },
    {
        "fix_commit_hash": "c350e1db257c13813fb52af8c5b6f62940dd289b",
        "repo_name": "pulsar",
        "best_scenario_issue_date": "2018-02-28T20:00:38-08:00"
    },
    {
        "fix_commit_hash": "7cd28b9d5cc862fe239f5e8fa1ca616237764607",
        "repo_name": "pulsar",
        "best_scenario_issue_date": "2020-05-08T11:05:09+08:00"
    }
]