[
    {
        "fix_commit_hash": "94ec03111369e694f432ca219be77820648d2188",
        "repo_name": "pulsar",
        "best_scenario_issue_date": "2021-06-22T18:12:06+08:00"
    },
    {
        "fix_commit_hash": "05ca2b546b9f68ce9d4a8166b92b40239c5cbe0f",
        "repo_name": "pulsar",
        "best_scenario_issue_date": "2021-06-25T04:27:32+03:00"
    },
    {
        "fix_commit_hash": "fdd7170d83807313188e9f270572e530dcb939ca",
        "repo_name": "pulsar",
        "best_scenario_issue_date": "2021-08-17T18:19:14+01:00"
    },
    {
        "fix_commit_hash": "dea574b3c6af7ea8eaa4904d8d6ed1044df00642",
        "repo_name": "pulsar",
        "best_scenario_issue_date": "2020-09-18T10:19:30+08:00"
    },
    {
        "fix_commit_hash": "e93a4c37b40040c336a03c2c08cebcaa99ac5cc3",
        "repo_name": "pulsar",
        "best_scenario_issue_date": "2017-05-30T18:11:20-07:00"
    },
    {
        "fix_commit_hash": "07c46fe9ef42a72de18be3267e70a51bbc883678",
        "repo_name": "pulsar",
        "best_scenario_issue_date": "2022-07-01T04:06:58+01:00"
    },
    {
        "fix_commit_hash": "700131bab6bfd7746f40ad362ea96f9f2ef339c4",
        "repo_name": "pulsar",
        "best_scenario_issue_date": "2020-10-02T11:31:37-07:00"
    },
    {
        "fix_commit_hash": "d7158dd872d80c5579e5f328b75b9d65cf6ea464",
        "repo_name": "pulsar",
        "best_scenario_issue_date": "2021-12-01T13:18:33-08:00"
    },
    {
        "fix_commit_hash": "43b3622cc7e7f746ca9920fdc704dc7448767ac7",
        "repo_name": "pulsar",
        "best_scenario_issue_date": "2023-06-03T21:15:16+08:00"
    },
    {
        "fix_commit_hash": "c14d079fa992d308e5ae04f7e7d0b9ada4f28cac",
        "repo_name": "pulsar",
        "best_scenario_issue_date": "2021-10-08T14:58:57+08:00"
    }
]